{
  "meta": {
    "generated_at": "2026-05-29T17:32:37.188497Z",
    "source_url": "https://www.cdep.ro/ords/pls/dic/declaratii2015.deputati?tip=ai&leg=2020",
    "scraper_version": "0.1.0",
    "count": 6
  },
  "data": {
    "id": "78825c4bf7c8fb91",
    "cdep_idm": 312,
    "deputat_nume": "Turcan Raluca",
    "deputat_canonical_id": "12bddf1fd4881aaf",
    "legislatura": 2020,
    "partid_short": "PNL",
    "declaratii": [
      {
        "data_depunere": "2020-12-30",
        "pdf_url": "https://www.cdep.ro/declaratii/deputati/2020/avere/312.pdf",
        "text_extracted": false,
        "error": "PDF scanat (text < 100 chars)",
        "terenuri_count": 0,
        "cladiri_count": 0,
        "suprafata_total_mp": 0.0,
        "suprafata_agricol_mp": 0.0,
        "suprafata_forestier_mp": 0.0,
        "suprafata_intravilan_mp": 0.0,
        "suprafata_luciu_mp": 0.0,
        "suprafata_alte_mp": 0.0,
        "suprafata_cladiri_mp": 0.0,
        "auto_count": 0,
        "bijuterii_total_ron": 0.0,
        "bunuri_instrainate_count": 0,
        "bunuri_instrainate_total_ron": 0.0,
        "conturi_total_ron": 0.0,
        "plasamente_total_ron": 0.0,
        "datorii_total_ron": 0.0,
        "cadouri_total_ron": 0.0,
        "venituri_anuale_ron": 0.0,
        "imobile_detaliate": [],
        "vehicule": [],
        "conturi_detaliate": [],
        "plasamente_detaliate": [],
        "total_active_monetare_ron": 0.0,
        "avere_neta_ron": 0.0,
        "nr_judete": 0,
        "nr_companii": 0,
        "terenuri_forestiere_count": 0,
        "terenuri_agricole_count": 0,
        "an_prima_proprietate": null
      },
      {
        "data_depunere": "2021-06-15",
        "pdf_url": "https://www.cdep.ro/declaratii/deputati/2020/avere/312a.pdf",
        "text_extracted": false,
        "error": "PDF scanat (text < 100 chars)",
        "terenuri_count": 0,
        "cladiri_count": 0,
        "suprafata_total_mp": 0.0,
        "suprafata_agricol_mp": 0.0,
        "suprafata_forestier_mp": 0.0,
        "suprafata_intravilan_mp": 0.0,
        "suprafata_luciu_mp": 0.0,
        "suprafata_alte_mp": 0.0,
        "suprafata_cladiri_mp": 0.0,
        "auto_count": 0,
        "bijuterii_total_ron": 0.0,
        "bunuri_instrainate_count": 0,
        "bunuri_instrainate_total_ron": 0.0,
        "conturi_total_ron": 0.0,
        "plasamente_total_ron": 0.0,
        "datorii_total_ron": 0.0,
        "cadouri_total_ron": 0.0,
        "venituri_anuale_ron": 0.0,
        "imobile_detaliate": [],
        "vehicule": [],
        "conturi_detaliate": [],
        "plasamente_detaliate": [],
        "total_active_monetare_ron": 0.0,
        "avere_neta_ron": 0.0,
        "nr_judete": 0,
        "nr_companii": 0,
        "terenuri_forestiere_count": 0,
        "terenuri_agricole_count": 0,
        "an_prima_proprietate": null
      },
      {
        "data_depunere": "2022-06-14",
        "pdf_url": "https://www.cdep.ro/declaratii/deputati/2020/avere/312b.pdf",
        "text_extracted": false,
        "error": "PDF scanat (text < 100 chars)",
        "terenuri_count": 0,
        "cladiri_count": 0,
        "suprafata_total_mp": 0.0,
        "suprafata_agricol_mp": 0.0,
        "suprafata_forestier_mp": 0.0,
        "suprafata_intravilan_mp": 0.0,
        "suprafata_luciu_mp": 0.0,
        "suprafata_alte_mp": 0.0,
        "suprafata_cladiri_mp": 0.0,
        "auto_count": 0,
        "bijuterii_total_ron": 0.0,
        "bunuri_instrainate_count": 0,
        "bunuri_instrainate_total_ron": 0.0,
        "conturi_total_ron": 0.0,
        "plasamente_total_ron": 0.0,
        "datorii_total_ron": 0.0,
        "cadouri_total_ron": 0.0,
        "venituri_anuale_ron": 0.0,
        "imobile_detaliate": [],
        "vehicule": [],
        "conturi_detaliate": [],
        "plasamente_detaliate": [],
        "total_active_monetare_ron": 0.0,
        "avere_neta_ron": 0.0,
        "nr_judete": 0,
        "nr_companii": 0,
        "terenuri_forestiere_count": 0,
        "terenuri_agricole_count": 0,
        "an_prima_proprietate": null
      },
      {
        "data_depunere": "2023-06-15",
        "pdf_url": "https://www.cdep.ro/declaratii/deputati/2020/avere/312c.pdf",
        "text_extracted": true,
        "error": null,
        "terenuri_count": 2,
        "cladiri_count": 1,
        "suprafata_total_mp": 4102.0,
        "suprafata_agricol_mp": 3000.0,
        "suprafata_forestier_mp": 0.0,
        "suprafata_intravilan_mp": 0.0,
        "suprafata_luciu_mp": 1000.0,
        "suprafata_alte_mp": 0.0,
        "suprafata_cladiri_mp": 102.0,
        "auto_count": 1,
        "bijuterii_total_ron": 75750.0,
        "bunuri_instrainate_count": 0,
        "bunuri_instrainate_total_ron": 0.0,
        "conturi_total_ron": 2600943.4,
        "plasamente_total_ron": 77930.0,
        "datorii_total_ron": 30322.0,
        "cadouri_total_ron": 0.0,
        "venituri_anuale_ron": 478488.0,
        "imobile_detaliate": [
          {
            "tip": "teren",
            "categorie": "agricol",
            "suprafata_mp": 3000.0,
            "judet": "Contract",
            "an_dobandirii": 2006,
            "cota_parte": null,
            "modul_dobandirii": "cumparare"
          },
          {
            "tip": "teren",
            "categorie": "luciu_apa",
            "suprafata_mp": 1000.0,
            "judet": "Ilfov",
            "an_dobandirii": 2006,
            "cota_parte": null,
            "modul_dobandirii": "cumparare"
          },
          {
            "tip": "cladire",
            "categorie": "comercial",
            "suprafata_mp": 102.0,
            "judet": "Sibiu",
            "an_dobandirii": 2017,
            "cota_parte": null,
            "modul_dobandirii": "cumparare"
          }
        ],
        "vehicule": [
          {
            "natura": "Autovehicul",
            "marca": "Toyota",
            "an_fabricatie": 2008,
            "mod_dobandire": "cumparare"
          }
        ],
        "conturi_detaliate": [
          {
            "institutie": "BRD",
            "tip": "cont_curent",
            "valuta": "RON",
            "an_deschis": 2009,
            "sold_ron": 5200.0
          },
          {
            "institutie": "BRD",
            "tip": "cont_curent",
            "valuta": "RON",
            "an_deschis": 2009,
            "sold_ron": 20000.0
          },
          {
            "institutie": "BRD",
            "tip": "cont_curent",
            "valuta": "EUR",
            "an_deschis": 2017,
            "sold_ron": 29391.0
          },
          {
            "institutie": "BRD",
            "tip": "cont_curent",
            "valuta": "RON",
            "an_deschis": 2016,
            "sold_ron": 24692.0
          },
          {
            "institutie": "BRD",
            "tip": "cont_curent",
            "valuta": "EUR",
            "an_deschis": 2017,
            "sold_ron": 1527377.55
          },
          {
            "institutie": null,
            "tip": "fond_investitii",
            "valuta": "RON",
            "an_deschis": 2014,
            "sold_ron": 21000.0
          },
          {
            "institutie": "BCR Asigurari",
            "tip": "fond_investitii",
            "valuta": "RON",
            "an_deschis": 2013,
            "sold_ron": 23450.0
          },
          {
            "institutie": "BCR Asigurari",
            "tip": "fond_investitii",
            "valuta": "RON",
            "an_deschis": 2013,
            "sold_ron": 6718.0
          },
          {
            "institutie": "BCR Asigurari",
            "tip": "fond_investitii",
            "valuta": "RON",
            "an_deschis": 2006,
            "sold_ron": 146000.0
          },
          {
            "institutie": "Raluca Turcan",
            "tip": "fond_investitii",
            "valuta": "EUR",
            "an_deschis": 2019,
            "sold_ron": 501151.89999999997
          },
          {
            "institutie": "NN Asigurari",
            "tip": "fond_investitii",
            "valuta": "RON",
            "an_deschis": 2006,
            "sold_ron": 36000.0
          },
          {
            "institutie": "NN Asigurari",
            "tip": "fond_investitii",
            "valuta": "RON",
            "an_deschis": 2019,
            "sold_ron": 6054.0
          },
          {
            "institutie": "NN Asigurari",
            "tip": "fond_investitii",
            "valuta": "EUR",
            "an_deschis": 2022,
            "sold_ron": 253908.94999999998
          }
        ],
        "plasamente_detaliate": [
          {
            "emitent": "1911",
            "tip": "imprumut",
            "nr_titluri": null,
            "valoare_ron": 1230.0
          },
          {
            "emitent": null,
            "tip": "imprumut",
            "nr_titluri": "98 %",
            "valoare_ron": 2200.0
          },
          {
            "emitent": null,
            "tip": null,
            "nr_titluri": "50 %",
            "valoare_ron": 1000.0
          },
          {
            "emitent": null,
            "tip": null,
            "nr_titluri": "100 %",
            "valoare_ron": 500.0
          },
          {
            "emitent": "Titluri de Stat Fidelis deţinute (titluri de stat, 180",
            "tip": "titluri_stat",
            "nr_titluri": null,
            "valoare_ron": 18000.0
          },
          {
            "emitent": "1",
            "tip": "imprumut",
            "nr_titluri": null,
            "valoare_ron": 55000.0
          }
        ],
        "total_active_monetare_ron": 2754623.4,
        "avere_neta_ron": 2724301.4,
        "nr_judete": 3,
        "nr_companii": 6,
        "terenuri_forestiere_count": 0,
        "terenuri_agricole_count": 1,
        "an_prima_proprietate": 2006
      },
      {
        "data_depunere": "2024-06-17",
        "pdf_url": "https://www.cdep.ro/declaratii/deputati/2020/avere/312d.pdf",
        "text_extracted": true,
        "error": null,
        "terenuri_count": 2,
        "cladiri_count": 2,
        "suprafata_total_mp": 4172.0,
        "suprafata_agricol_mp": 3000.0,
        "suprafata_forestier_mp": 0.0,
        "suprafata_intravilan_mp": 0.0,
        "suprafata_luciu_mp": 1000.0,
        "suprafata_alte_mp": 0.0,
        "suprafata_cladiri_mp": 172.0,
        "auto_count": 0,
        "bijuterii_total_ron": 90900.0,
        "bunuri_instrainate_count": 1,
        "bunuri_instrainate_total_ron": 25250.0,
        "conturi_total_ron": 2872257.1999999997,
        "plasamente_total_ron": 77930.0,
        "datorii_total_ron": 80322.0,
        "cadouri_total_ron": 0.0,
        "venituri_anuale_ron": 546974.0,
        "imobile_detaliate": [
          {
            "tip": "teren",
            "categorie": "agricol",
            "suprafata_mp": 3000.0,
            "judet": "Contract",
            "an_dobandirii": 2006,
            "cota_parte": null,
            "modul_dobandirii": "cumparare"
          },
          {
            "tip": "teren",
            "categorie": "luciu_apa",
            "suprafata_mp": 1000.0,
            "judet": "Ilfov",
            "an_dobandirii": 2006,
            "cota_parte": null,
            "modul_dobandirii": "cumparare"
          },
          {
            "tip": "cladire",
            "categorie": "apartament",
            "suprafata_mp": 102.0,
            "judet": "Sibiu",
            "an_dobandirii": 2017,
            "cota_parte": null,
            "modul_dobandirii": "cumparare"
          },
          {
            "tip": "cladire",
            "categorie": "comercial",
            "suprafata_mp": 70.0,
            "judet": "Contract",
            "an_dobandirii": 2023,
            "cota_parte": null,
            "modul_dobandirii": "cumparare"
          }
        ],
        "vehicule": [],
        "conturi_detaliate": [
          {
            "institutie": "BRD",
            "tip": "cont_curent",
            "valuta": "RON",
            "an_deschis": 2009,
            "sold_ron": 26746.0
          },
          {
            "institutie": "BRD",
            "tip": "cont_curent",
            "valuta": "RON",
            "an_deschis": 2009,
            "sold_ron": 2110.0
          },
          {
            "institutie": "BRD",
            "tip": "cont_curent",
            "valuta": "EUR",
            "an_deschis": 2017,
            "sold_ron": 25401.5
          },
          {
            "institutie": "BRD",
            "tip": "cont_curent",
            "valuta": "RON",
            "an_deschis": 2016,
            "sold_ron": 9076.0
          },
          {
            "institutie": "BRD",
            "tip": "cont_curent",
            "valuta": "EUR",
            "an_deschis": 2017,
            "sold_ron": 426704.8
          },
          {
            "institutie": null,
            "tip": "fond_investitii",
            "valuta": "RON",
            "an_deschis": 2014,
            "sold_ron": 22990.0
          },
          {
            "institutie": "BCR Asigurari",
            "tip": "fond_investitii",
            "valuta": "RON",
            "an_deschis": 2013,
            "sold_ron": 23450.0
          },
          {
            "institutie": "BCR Asigurari",
            "tip": "fond_investitii",
            "valuta": "RON",
            "an_deschis": 2013,
            "sold_ron": 6718.0
          },
          {
            "institutie": "BCR Asigurari",
            "tip": "fond_investitii",
            "valuta": "RON",
            "an_deschis": 2006,
            "sold_ron": 170000.0
          },
          {
            "institutie": "Raluca Turcan",
            "tip": "fond_investitii",
            "valuta": "EUR",
            "an_deschis": 2019,
            "sold_ron": 501343.8
          },
          {
            "institutie": "NN Asigurari",
            "tip": "fond_investitii",
            "valuta": "RON",
            "an_deschis": 2006,
            "sold_ron": 50000.0
          },
          {
            "institutie": "NN Asigurari",
            "tip": "fond_investitii",
            "valuta": "RON",
            "an_deschis": 2019,
            "sold_ron": 43086.0
          },
          {
            "institutie": "NN Asigurari",
            "tip": "fond_investitii",
            "valuta": "EUR",
            "an_deschis": 2022,
            "sold_ron": 255797.65
          },
          {
            "institutie": "NN Asigurari",
            "tip": "depozit",
            "valuta": "RON",
            "an_deschis": 2023,
            "sold_ron": 300000.0
          },
          {
            "institutie": null,
            "tip": "depozit",
            "valuta": "EUR",
            "an_deschis": 2023,
            "sold_ron": 503833.44999999995
          },
          {
            "institutie": null,
            "tip": "fond_investitii",
            "valuta": "EUR",
            "an_deschis": 2023,
            "sold_ron": 505000.0
          }
        ],
        "plasamente_detaliate": [
          {
            "emitent": "1911",
            "tip": "imprumut",
            "nr_titluri": null,
            "valoare_ron": 1230.0
          },
          {
            "emitent": null,
            "tip": "imprumut",
            "nr_titluri": "98 %",
            "valoare_ron": 2200.0
          },
          {
            "emitent": null,
            "tip": null,
            "nr_titluri": "50 %",
            "valoare_ron": 1000.0
          },
          {
            "emitent": null,
            "tip": null,
            "nr_titluri": "100 %",
            "valoare_ron": 500.0
          },
          {
            "emitent": "Titluri de Stat Fidelis deţinute (titluri de stat, 180",
            "tip": "titluri_stat",
            "nr_titluri": null,
            "valoare_ron": 18000.0
          },
          {
            "emitent": "1",
            "tip": "imprumut",
            "nr_titluri": null,
            "valoare_ron": 55000.0
          }
        ],
        "total_active_monetare_ron": 3041087.1999999997,
        "avere_neta_ron": 2960765.1999999997,
        "nr_judete": 3,
        "nr_companii": 6,
        "terenuri_forestiere_count": 0,
        "terenuri_agricole_count": 1,
        "an_prima_proprietate": 2006
      },
      {
        "data_depunere": "2025-01-20",
        "pdf_url": "https://www.cdep.ro/declaratii/deputati/2020/avere/312e.pdf",
        "text_extracted": true,
        "error": null,
        "terenuri_count": 2,
        "cladiri_count": 2,
        "suprafata_total_mp": 4172.0,
        "suprafata_agricol_mp": 3000.0,
        "suprafata_forestier_mp": 0.0,
        "suprafata_intravilan_mp": 0.0,
        "suprafata_luciu_mp": 1000.0,
        "suprafata_alte_mp": 0.0,
        "suprafata_cladiri_mp": 172.0,
        "auto_count": 0,
        "bijuterii_total_ron": 139885.0,
        "bunuri_instrainate_count": 0,
        "bunuri_instrainate_total_ron": 0.0,
        "conturi_total_ron": 1994168.0999999999,
        "plasamente_total_ron": 459930.0,
        "datorii_total_ron": 80322.0,
        "cadouri_total_ron": 0.0,
        "venituri_anuale_ron": 766202.0,
        "imobile_detaliate": [
          {
            "tip": "teren",
            "categorie": "agricol",
            "suprafata_mp": 3000.0,
            "judet": "Contract",
            "an_dobandirii": 2006,
            "cota_parte": null,
            "modul_dobandirii": "cumparare"
          },
          {
            "tip": "teren",
            "categorie": "luciu_apa",
            "suprafata_mp": 1000.0,
            "judet": "Ilfov",
            "an_dobandirii": 2006,
            "cota_parte": null,
            "modul_dobandirii": "cumparare"
          },
          {
            "tip": "cladire",
            "categorie": "apartament",
            "suprafata_mp": 102.0,
            "judet": "Sibiu",
            "an_dobandirii": 2017,
            "cota_parte": null,
            "modul_dobandirii": "cumparare"
          },
          {
            "tip": "cladire",
            "categorie": "comercial",
            "suprafata_mp": 70.0,
            "judet": "Contract",
            "an_dobandirii": 2023,
            "cota_parte": null,
            "modul_dobandirii": "cumparare"
          }
        ],
        "vehicule": [],
        "conturi_detaliate": [
          {
            "institutie": "BRD",
            "tip": "cont_curent",
            "valuta": "RON",
            "an_deschis": 2009,
            "sold_ron": 26746.0
          },
          {
            "institutie": "BRD",
            "tip": "cont_curent",
            "valuta": "RON",
            "an_deschis": 2009,
            "sold_ron": 2110.0
          },
          {
            "institutie": "BRD",
            "tip": "cont_curent",
            "valuta": "EUR",
            "an_deschis": 2017,
            "sold_ron": 40400.0
          },
          {
            "institutie": "BRD",
            "tip": "cont_curent",
            "valuta": "RON",
            "an_deschis": 2016,
            "sold_ron": 48639.0
          },
          {
            "institutie": "BRD",
            "tip": "cont_curent",
            "valuta": "EUR",
            "an_deschis": 2017,
            "sold_ron": 161302.05
          },
          {
            "institutie": null,
            "tip": "fond_investitii",
            "valuta": "RON",
            "an_deschis": 2014,
            "sold_ron": 24130.0
          },
          {
            "institutie": "BCR Asigurari",
            "tip": "fond_investitii",
            "valuta": "RON",
            "an_deschis": 2013,
            "sold_ron": 23450.0
          },
          {
            "institutie": "BCR Asigurari",
            "tip": "fond_investitii",
            "valuta": "RON",
            "an_deschis": 2013,
            "sold_ron": 6718.0
          },
          {
            "institutie": "BCR Asigurari",
            "tip": "fond_investitii",
            "valuta": "RON",
            "an_deschis": 2006,
            "sold_ron": 170000.0
          },
          {
            "institutie": "Raluca Turcan",
            "tip": "fond_investitii",
            "valuta": "EUR",
            "an_deschis": 2019,
            "sold_ron": 508110.8
          },
          {
            "institutie": "NN Asigurari",
            "tip": "fond_investitii",
            "valuta": "RON",
            "an_deschis": 2006,
            "sold_ron": 50000.0
          },
          {
            "institutie": "NN Asigurari",
            "tip": "fond_investitii",
            "valuta": "RON",
            "an_deschis": 2019,
            "sold_ron": 108294.0
          },
          {
            "institutie": "NN Asigurari",
            "tip": "fond_investitii",
            "valuta": "RON",
            "an_deschis": 2023,
            "sold_ron": 40000.0
          },
          {
            "institutie": "NN Asigurari",
            "tip": "depozit",
            "valuta": "EUR",
            "an_deschis": 2023,
            "sold_ron": 599010.7999999999
          },
          {
            "institutie": null,
            "tip": "fond_investitii",
            "valuta": "EUR",
            "an_deschis": 2023,
            "sold_ron": 31759.449999999997
          },
          {
            "institutie": null,
            "tip": "fond_investitii",
            "valuta": "RON",
            "an_deschis": 2024,
            "sold_ron": 3000.0
          },
          {
            "institutie": null,
            "tip": "fond_investitii",
            "valuta": "EUR",
            "an_deschis": 2024,
            "sold_ron": 25502.5
          },
          {
            "institutie": null,
            "tip": "fond_investitii",
            "valuta": "EUR",
            "an_deschis": 2024,
            "sold_ron": 4595.5
          },
          {
            "institutie": "PENSIEPILON2VT",
            "tip": "fond_investitii",
            "valuta": "RON",
            "an_deschis": 2000,
            "sold_ron": 115000.0
          },
          {
            "institutie": "PENSIEPILON2VT",
            "tip": "fond_investitii",
            "valuta": "USD",
            "an_deschis": 2024,
            "sold_ron": 5400.0
          }
        ],
        "plasamente_detaliate": [
          {
            "emitent": "1911",
            "tip": "imprumut",
            "nr_titluri": null,
            "valoare_ron": 1230.0
          },
          {
            "emitent": null,
            "tip": "imprumut",
            "nr_titluri": "98 %",
            "valoare_ron": 2200.0
          },
          {
            "emitent": "Valeriu Turcan SC Acţiuni sau părţi sociale",
            "tip": null,
            "nr_titluri": "50 %",
            "valoare_ron": 1000.0
          },
          {
            "emitent": null,
            "tip": null,
            "nr_titluri": "100 %",
            "valoare_ron": 500.0
          },
          {
            "emitent": "Titluri de Stat Fidelis deţinute (titluri de stat, 180",
            "tip": "titluri_stat",
            "nr_titluri": null,
            "valoare_ron": 200000.0
          },
          {
            "emitent": "1",
            "tip": "imprumut",
            "nr_titluri": null,
            "valoare_ron": 55000.0
          },
          {
            "emitent": "PNL 1",
            "tip": "imprumut",
            "nr_titluri": null,
            "valoare_ron": 200000.0
          }
        ],
        "total_active_monetare_ron": 2593983.0999999996,
        "avere_neta_ron": 2513661.0999999996,
        "nr_judete": 3,
        "nr_companii": 7,
        "terenuri_forestiere_count": 0,
        "terenuri_agricole_count": 1,
        "an_prima_proprietate": 2006
      }
    ],
    "ultima_data": "2025-01-20",
    "ultima_conturi_ron": 1994168.0999999999,
    "ultima_venituri_ron": 766202.0,
    "ultima_imobile_count": 4,
    "ultima_bijuterii_ron": 139885.0,
    "ultima_plasamente_ron": 459930.0,
    "ultima_datorii_ron": 80322.0,
    "ultima_total_active_ron": 2593983.0999999996,
    "ultima_avere_neta_ron": 2513661.0999999996,
    "ultima_nr_judete": 3,
    "ultima_nr_companii": 7,
    "delta_conturi_ron": 1994168.0999999999,
    "delta_imobile": 4
  }
}