{
  "meta": {
    "generated_at": "2026-05-29T17:21:55.608313Z",
    "source_url": "https://www.cdep.ro/ords/pls/dic/declaratii2015.deputati?tip=ai&leg=2024",
    "scraper_version": "0.1.0",
    "count": 1
  },
  "data": {
    "id": "92531a80d983775a",
    "cdep_idm": 145,
    "deputat_nume": "Iancu Marius-Ionel",
    "deputat_canonical_id": "630230e548c1799e",
    "legislatura": 2024,
    "partid_short": "PSD",
    "declaratii": [
      {
        "data_depunere": "2024-12-29",
        "pdf_url": "https://www.cdep.ro/declaratii/deputati/2024/avere/145.pdf",
        "text_extracted": true,
        "error": null,
        "terenuri_count": 20,
        "cladiri_count": 2,
        "suprafata_total_mp": 27652.0,
        "suprafata_agricol_mp": 25716.0,
        "suprafata_forestier_mp": 0.0,
        "suprafata_intravilan_mp": 0.0,
        "suprafata_luciu_mp": 1791.0,
        "suprafata_alte_mp": 0.0,
        "suprafata_cladiri_mp": 145.0,
        "auto_count": 2,
        "bijuterii_total_ron": 0.0,
        "bunuri_instrainate_count": 0,
        "bunuri_instrainate_total_ron": 0.0,
        "conturi_total_ron": 30643.4,
        "plasamente_total_ron": 150000.0,
        "datorii_total_ron": 143000.0,
        "cadouri_total_ron": 0.0,
        "venituri_anuale_ron": 222794.0,
        "imobile_detaliate": [
          {
            "tip": "teren",
            "categorie": "agricol",
            "suprafata_mp": 3728.0,
            "judet": "Olt",
            "an_dobandirii": 2021,
            "cota_parte": "1/1",
            "modul_dobandirii": null
          },
          {
            "tip": "teren",
            "categorie": "agricol",
            "suprafata_mp": 300.0,
            "judet": "Olt",
            "an_dobandirii": 2021,
            "cota_parte": "1/1",
            "modul_dobandirii": null
          },
          {
            "tip": "teren",
            "categorie": "agricol",
            "suprafata_mp": 1940.0,
            "judet": "Olt",
            "an_dobandirii": 2021,
            "cota_parte": "1/1",
            "modul_dobandirii": null
          },
          {
            "tip": "teren",
            "categorie": "agricol",
            "suprafata_mp": 2609.0,
            "judet": "Olt",
            "an_dobandirii": 2021,
            "cota_parte": "1/1",
            "modul_dobandirii": null
          },
          {
            "tip": "teren",
            "categorie": "agricol",
            "suprafata_mp": 2413.0,
            "judet": "Olt",
            "an_dobandirii": 2021,
            "cota_parte": "1/1",
            "modul_dobandirii": null
          },
          {
            "tip": "teren",
            "categorie": "agricol",
            "suprafata_mp": 6100.0,
            "judet": "Olt",
            "an_dobandirii": 2021,
            "cota_parte": "1/1",
            "modul_dobandirii": null
          },
          {
            "tip": "teren",
            "categorie": "agricol",
            "suprafata_mp": 500.0,
            "judet": "Olt",
            "an_dobandirii": 2021,
            "cota_parte": "1/1",
            "modul_dobandirii": null
          },
          {
            "tip": "teren",
            "categorie": "agricol",
            "suprafata_mp": 3880.0,
            "judet": "Olt",
            "an_dobandirii": 2021,
            "cota_parte": "1/1",
            "modul_dobandirii": null
          },
          {
            "tip": "teren",
            "categorie": "agricol",
            "suprafata_mp": 4246.0,
            "judet": "Olt",
            "an_dobandirii": 2021,
            "cota_parte": "1/1",
            "modul_dobandirii": null
          },
          {
            "tip": "teren",
            "categorie": "luciu_apa",
            "suprafata_mp": 1791.0,
            "judet": "Olt",
            "an_dobandirii": 2021,
            "cota_parte": "1/1",
            "modul_dobandirii": null
          },
          {
            "tip": "cladire",
            "categorie": "comercial",
            "suprafata_mp": 145.0,
            "judet": "Olt",
            "an_dobandirii": 2021,
            "cota_parte": "1/1",
            "modul_dobandirii": null
          }
        ],
        "vehicule": [
          {
            "natura": "Autoturism",
            "marca": "BMW",
            "an_fabricatie": 2017,
            "mod_dobandire": null
          },
          {
            "natura": "Autoturism",
            "marca": "CHEVROLET",
            "an_fabricatie": 2009,
            "mod_dobandire": null
          }
        ],
        "conturi_detaliate": [
          {
            "institutie": null,
            "tip": "cont_curent",
            "valuta": "RON",
            "an_deschis": 2018,
            "sold_ron": 14500.0
          },
          {
            "institutie": null,
            "tip": "cont_curent",
            "valuta": "EUR",
            "an_deschis": 2018,
            "sold_ron": 40.4
          },
          {
            "institutie": "RAIFFEISEN",
            "tip": "cont_curent",
            "valuta": "RON",
            "an_deschis": 2022,
            "sold_ron": 3000.0
          },
          {
            "institutie": "NN ASIGURARI",
            "tip": "fond_investitii",
            "valuta": "RON",
            "an_deschis": 2015,
            "sold_ron": 8600.0
          },
          {
            "institutie": "NN ASIGURARI",
            "tip": "fond_investitii",
            "valuta": "RON",
            "an_deschis": 2011,
            "sold_ron": 4503.0
          }
        ],
        "plasamente_detaliate": [
          {
            "emitent": "1",
            "tip": "imprumut",
            "nr_titluri": null,
            "valoare_ron": 150000.0
          }
        ],
        "total_active_monetare_ron": 180643.4,
        "avere_neta_ron": 37643.399999999994,
        "nr_judete": 1,
        "nr_companii": 1,
        "terenuri_forestiere_count": 0,
        "terenuri_agricole_count": 9,
        "an_prima_proprietate": 2021
      }
    ],
    "ultima_data": "2024-12-29",
    "ultima_conturi_ron": 30643.4,
    "ultima_venituri_ron": 222794.0,
    "ultima_imobile_count": 22,
    "ultima_bijuterii_ron": 0.0,
    "ultima_plasamente_ron": 150000.0,
    "ultima_datorii_ron": 143000.0,
    "ultima_total_active_ron": 180643.4,
    "ultima_avere_neta_ron": 37643.399999999994,
    "ultima_nr_judete": 1,
    "ultima_nr_companii": 1,
    "delta_conturi_ron": 0.0,
    "delta_imobile": 0
  }
}