{
  "meta": {
    "generated_at": "2026-05-26T19:01:40.586345Z",
    "source_url": "https://www.cdep.ro/ords/pls/dic/declaratii2015.deputati?tip=ai&leg=2024",
    "scraper_version": "0.1.0",
    "count": 2
  },
  "data": {
    "id": "447166374e9d402b",
    "cdep_idm": 230,
    "deputat_nume": "Oancea Silviu-Florin",
    "deputat_canonical_id": "500c2026b4590ed7",
    "legislatura": 2024,
    "partid_short": "AUR",
    "declaratii": [
      {
        "data_depunere": "2025-01-20",
        "pdf_url": "https://www.cdep.ro/declaratii/deputati/2024/avere/230.pdf",
        "text_extracted": true,
        "error": null,
        "terenuri_count": 1,
        "cladiri_count": 5,
        "suprafata_total_mp": 794.0,
        "conturi_total_ron": 1120200.0,
        "venituri_anuale_ron": 1394159.0,
        "datorii_total_ron": 831622.0,
        "auto_count": 11,
        "imobile_detaliate": []
      },
      {
        "data_depunere": "2025-03-03",
        "pdf_url": "https://www.cdep.ro/declaratii/deputati/2024/avere/230a.pdf",
        "text_extracted": true,
        "error": null,
        "terenuri_count": 1,
        "cladiri_count": 5,
        "suprafata_total_mp": 794.0,
        "conturi_total_ron": 1120200.0,
        "venituri_anuale_ron": 1496159.0,
        "datorii_total_ron": 831622.0,
        "auto_count": 11,
        "imobile_detaliate": []
      }
    ],
    "ultima_data": "2025-03-03",
    "ultima_conturi_ron": 1120200.0,
    "ultima_venituri_ron": 1496159.0,
    "ultima_imobile_count": 6,
    "delta_conturi_ron": 0.0,
    "delta_imobile": 0
  }
}